<annotation>
	<folder>black_4</folder>
	<filename>IMG_0433.JPG</filename>
	<path>/Users/egemeneroglu/PycharmProjects/101_project/tiles/black/black_4/IMG_0433.JPG</path>
	<source>
		<database>Unknown</database>
	</source>
	<size>
		<width>3024</width>
		<height>4032</height>
		<depth>3</depth>
	</size>
	<segmented>0</segmented>
	<object>
		<name>black_4</name>
		<pose>Unspecified</pose>
		<truncated>0</truncated>
		<difficult>0</difficult>
		<bndbox>
			<xmin>323</xmin>
			<ymin>394</ymin>
			<xmax>2499</xmax>
			<ymax>3485</ymax>
		</bndbox>
	</object>
</annotation>
